{
    "icons": [ "awesome-fonts" ],
    "defaults": {
        "separator-block-width": 0,
        "separator": "",
        "warning": {
          "     fg": "#808080",
			    "bg": "#285577"
		    },
    		"critical": {
    			"fg": "#282A36",
    			"bg": "#FF5555"
    		},
        "fg": "#efefef",
        "bg": "#161821"
    },
    "battery": {
        "charged": {
            "fg": "#5fafff",
            "bg": "#161821"
        },
        "charging": {
            "fg": "#89b8c2",
            "bg": "#161821"
        }
    },
    "date": {
        "fg": "#5fafff",
        "bg": "#161821"
    }
}
